vbdiar/__init__.py
vbdiar/vb.py
vbdiar-0.0.1.dist-info/METADATA
vbdiar-0.0.1.dist-info/WHEEL
vbdiar-0.0.1.dist-info/top_level.txt
vbdiar-0.0.1.dist-info/RECORD
