Metadata-Version: 2.1
Name: vbdiar
Version: 0.0.1
Summary: VB Diarization with Eigenvoice and HMM Priors
Home-page: https://github.com/wq2012/VB_diarization
Author: Quan Wang
Author-email: quanw@google.com
License: UNKNOWN
Platform: UNKNOWN
Classifier: Programming Language :: Python :: 3
Classifier: License :: OSI Approved :: Apache Software License
Classifier: Operating System :: OS Independent
